pyenergydiagrams/__init__.py
pyenergydiagrams/_version.py
pyenergydiagrams/main.py
pyenergydiagrams-1.0.1.dist-info/LICENSE
pyenergydiagrams-1.0.1.dist-info/METADATA
pyenergydiagrams-1.0.1.dist-info/WHEEL
pyenergydiagrams-1.0.1.dist-info/top_level.txt
pyenergydiagrams-1.0.1.dist-info/RECORD
